{
  "DialogueId": "TutMinigame",
  "Dialogue": {
    "da": [
      "<c=minigame_button>M-knapper</c> vil aktivere et minispil!",
      "Hvis du fejler, kan du prøve igen så mange gange, du vil.",
      "Du kan prøve minspillet igen ved at trykke på knappen igen.",
      "Døren ved slutningen fører dig tilbage hertil, hvis du ønsker at prøve igen.\nKom så, makker!"
    ],
    "en": [
      "<c=minigame_button>M-buttons</c> will activate a minigame!",
      "If you fail, you can retry as many times as you want.",
      "You can retry the minigame by hitting the button again.",
      "The door at the end will simply take you back here if you wish to retry.\nGo for it, champ!"
    ],

    "fr": [
      "<c=minigame_button>Les boutons M</c> lanceront un mini-jeu!",
      "En cas d'échec,vous pouvez réessayer autant de fois que vous le souhaitez.",
      "Vous pouvez retenter le mini-jeu en réappuyant sur le bouton.",
      "La porte se trouvant à la fin vous ramènera ici si vous souhaitez réessayer. \nAllez-y, champion!"
    ],
    "pt-BR": []
=======
    "pt-BR": [
      "<c=minigame_button>M-buttons</c> irá ativar um minijogo!",
      "Se você falhar, você pode tentar de novo quantas vezes quiser.",
      "Você pode tentar o minijogo novamente só por pressionar o botão de novo.",
      "A porta no final irá simplesmente te trazer de volta se você deseja tentar de novo. \nVai fundo, campeão!"
    ]
  },
  "Responses": {
    "da": [],
    "en": [],
    "fr": [],
    "pt-BR": []
  }
}